ColorTER/__init__.py
ColorTER-1.0.0.dist-info/LICENSE
ColorTER-1.0.0.dist-info/METADATA
ColorTER-1.0.0.dist-info/WHEEL
ColorTER-1.0.0.dist-info/top_level.txt
ColorTER-1.0.0.dist-info/RECORD
